[
  {
    "category": {
      "name": "animals",
      "image": "animals",
      "count": 100,
      "desc": {
        "en": "U2FsdGVkX18dKxzlDPajHClbw+Sl9xxZJ35PRVHPG2g=",
        "tr": "U2FsdGVkX19n8/jsx/LvWVr+7QEjHV255cfeHOBPi8s="
      },
      "alphabet": {
        "en": "ABCDEFGHIJKLMNOPQRSTUVWXYZ",
        "tr": "ABCÇDEFGĞHIİJKLMNOÖPRSŞTUÜVYZ"
      },
      "published": true,
      "licensed": false
    }
  },
  {
    "category": {
      "name": "musicalinstruments",
      "image": "musicalinstruments",
      "count": 40,
      "desc": {
        "en": "U2FsdGVkX19vcvWetWiEO0WpBFaFpxU4zEHuSR9isEs1KHqt4OkVsHEp5slijOOP",
        "tr": "U2FsdGVkX18p0NXnosrkfKC+wwuk3l7s5p6Ol9fc3E4c1LGVu2ywemj4ARcFxo6a"
      },
      "alphabet": {
        "en": "ABCDEFGHIJKLMNOPQRSTUVWXYZ",
        "tr": "ABCÇDEFGĞHIİJKLMNOÖPRSŞTUÜVYZ"
      },
      "published": true,
      "licensed": false
    }
  },
  {
    "category": {
      "name": "sports",
      "image": "sports",
      "count": 50,
      "desc": {
        "en": "U2FsdGVkX19GppWbcuI7LSO1BWuurJwJHlub5ZgH8FI=",
        "tr": "U2FsdGVkX192bUiEaAZg2UUZqgqmw8jNjPqkdcdeTU8="
      },
      "alphabet": {
        "en": "ABCDEFGHIJKLMNOPQRSTUVWXYZ",
        "tr": "ABCÇDEFGĞHIİJKLMNOÖPRSŞTUÜVYZ"
      },
      "published": true,
      "licensed": false
    }
  },
  {
    "category": {
      "name": "vehicles",
      "image": "vehicles",
      "count": 40,
      "desc": {
        "en": "U2FsdGVkX19judr7t4lReLmi6Cbt3GIF28FywJgG4bY=",
        "tr": "U2FsdGVkX19ZgLUbK5kji5TJ4AWbH0os1VV3nPoX7jg="
      },
      "alphabet": {
        "en": "ABCDEFGHIJKLMNOPQRSTUVWXYZ",
        "tr": "ABCÇDEFGĞHIİJKLMNOÖPRSŞTUÜVYZ"
      },
      "published": true,
      "licensed": false
    }
  },
  {
    "category": {
      "name": "professions",
      "image": "professions",
      "count": 1,
      "desc": {
        "en": "U2FsdGVkX19kRQosdL7udv6RkaJUEfT0Ivd0u9KWxAs=",
        "tr": "U2FsdGVkX19wIfrBKgxmXTMdsvpWP4K9xJ9t0W4ettg="
      },
      "alphabet": {
        "en": "ABCDEFGHIJKLMNOPQRSTUVWXYZ",
        "tr": "ABCÇDEFGĞHIİJKLMNOÖPRSŞTUÜVYZ"
      },
      "published": true,
      "licensed": false
    }
  }
]